{
  "date": "2026-04-16",
  "index_action": "高波動博弈，台積電法說會前夕籌碼大洗牌",
  "heavyweights_dumped": [
    "群創 (-13.3億)",
    "毅嘉 (-9.6億)",
    "友達 (-3.2億)",
    "恩德 (-2.6億)",
    "群益證 (-2.0億)"
  ],
  "safe_havens_bought": [
    "國巨 (+26.6億)",
    "廣達 (+24.3億)",
    "聯電 (+23.1億)",
    "南亞科 (+18.4億)",
    "南亞 (+18.4億)",
    "台塑 (+10.9億)"
  ],
  "sectors": {
    "AI 儲存基礎設施": [
      "旺宏 (2337): 技術位進入主升段，AI BIOS/Nor Flash 短缺預期"
    ],
    "AI PCB 材料族群": [
      "台玻 (1802): 主升段確認，成交量 2.41億股",
      "南亞 (1303): 外資大買 18.4億，基期低具補漲屬性"
    ],
    "AI 伺服器與系統整合": [
      "廣達 (2382): 外資佈局核心定錨點",
      "國巨 (2327): AI 伺服器被動元件買超榜首"
    ],
    "邊緣運算轉型": [
      "聯電 (2303): 爆量站穩 MA20，底部成型"
    ],
    "CPO 矽光子": [
      "富采 (3714): CPO 商轉黑馬"
    ],
    "面板級扇出型封裝 (FOPLP)": [
      "群創 (3481): 爆天量但外資瘋狂提款，被視為提款機",
      "友達 (2409): 誘多陷阱中心，法人後門撤退"
    ],
    "AI 記憶體關鍵材料": [
      "南亞科 (2408): 外資持續加碼"
    ],
    "車載與通訊軟板": [
      "毅嘉 (2402): 外資重砍，需警戒 MA20 支撐"
    ]
  },
  "ai_data_picks": [
    "旺宏 (外資投信同步買進，AI BIOS 進入機構定價階段)",
    "南亞 (外資大舉掃貨，AI 基礎材料底部補漲標的)"
  ],
  "commodities": [
    "黃金 $4832.9 (反映市場對高位科技股之避險情緒)"
  ],
  "conservative_strategy": "關注台塑、南亞等 AI 基礎材料族群，底部成型具防禦性；法說會前高波動期建議現金為王。",
  "aggressive_strategy": "持股旺宏與台玻等主升段標的，以 MA5 為防守點，未跌破前不預設壓力位。"
}