{
  "date": "2026-04-22",
  "index_action": "上漲 273.36 點",
  "heavyweights_dumped": [
    "1802 台玻 (-24.9億)",
    "0056 元大高股息 (-14.2億)",
    "00981A 主動統一台股增長 (-13.5億)",
    "2337 旺宏 (-12.8億)",
    "2481 強茂 (-9.0億)"
  ],
  "safe_havens_bought": [
    "2317 鴻海 (+88.5億)",
    "2303 聯電 (+37.6億)",
    "2301 光寶科 (+26.5億)",
    "2324 仁寶 (+16.1億)",
    "1303 南亞 (+12.7億)"
  ],
  "sectors": {
    "AI 伺服器垂直整合": [
      "2317 鴻海"
    ],
    "AI 伺服器輔助晶片": [
      "2303 聯電"
    ],
    "AI 伺服器電源管理": [
      "2301 光寶科"
    ],
    "AI 伺服器系統組裝": [
      "2324 仁寶"
    ],
    "AI PCB 材料": [
      "1303 南亞",
      "1802 台玻 (高位拋售)"
    ],
    "AI 記憶體整合技術": [
      "6770 力積電"
    ],
    "AI 儲存基礎設施": [
      "2337 旺宏"
    ],
    "AI 邊緣人機介面": [
      "2409 友達"
    ],
    "AI 先進封裝材料": [
      "3481 群創"
    ],
    "主動型 ETF": [
      "00981A 主動統一台股增長",
      "00992A 主動群益科技創新"
    ],
    "高股息/權重 ETF": [
      "00919 群益台灣精選高息",
      "009816 凱基台灣TOP50",
      "0056 元大高股息"
    ]
  },
  "ai_data_picks": [
    "2317 鴻海 (外資買超 88.5 億)",
    "2301 光寶科 (帶量突破 MA20)"
  ],
  "prediction_targets": [
    {
      "id": "2301",
      "name": "光寶科",
      "direction": "多",
      "trigger": "外資單日大買 26.5 億，帶量突破 MA20 關鍵壓力，RSI 進入攻擊區",
      "stop_loss_price": 163.7,
      "stop_loss_desc": "收盤跌破 163.7 元"
    },
    {
      "id": "2317",
      "name": "鴻海",
      "direction": "多",
      "trigger": "營收年增 58.5% 進入訂單爆發期，外資買超第 1 名，放量突破",
      "stop_loss_price": 210.5,
      "stop_loss_desc": "收盤跌破 210.5 元 (MA5)"
    }
  ],
  "prev_day_picks_result": [
    "2303 聯電 (+3.15%, 2.32億股, 預測成立)",
    "1802 台玻 (-4.45%, 2.01億股, 外資大賣24.9億, 預測不成立)",
    "2344 華邦電 (成功脫離底部, 預測成立)",
    "3231 緯創 (撐盤隨盤勢上行, 預測成立)"
  ],
  "price_volume_divergence": [
    "00981A 狂噴 5.04 億股天量且漲 26.94%，但外資反手賣超 13.5 億",
    "1802 台玻巨量收黑，成交量第 4 但股價跌 4.45% 且外資大賣 24.9 億",
    "2317 鴻海成交量僅第 14，但外資砸 88.5 億為買超第 1，呈現籌碼高度集中"
  ],
  "commodities": [
    "黃金漲 1.55%",
    "原油跌 1.64%"
  ],
  "conservative_strategy": "配置資金於 1303 南亞等具防禦屬性的 AI PCB 材料族群，現金水位保持在 20% 以應對震盪。",
  "aggressive_strategy": "鎖定外資重金灌入的核心硬體股，如 2317 鴻海與 2301 光寶科，於放量突破初期進場。"
}